{
  "domains": [
    {
      "name": "Software Engineering",
      "description": "Designing, developing, testing, and maintaining software systems.",
      "jobs": [
        {"name": "Software Engineer"},
        {"name": "Backend Developer"},
        {"name": "Frontend Developer"},
        {"name": "Full Stack Developer"},
        {"name": "Mobile Developer"},
        {"name": "QA Engineer"},
        {"name": "Software Architect"},
        {"name": "Engineering Lead"},
        {"name": "Solutions Engineer"},
        {"name": "Software Test Automation Engineer"},
        {"name": "API Developer"},
        {"name": "Desktop Application Developer"},
        {"name": "Integration Engineer"},
        {"name": "Release Manager"},
        {"name": "Performance Engineer"},
        {"name": "Systems Analyst"}
      ]
    },
    {
      "name": "Data Science & AI",
      "description": "Building intelligent systems using data analysis, ML, and AI techniques.",
      "jobs": [
        {"name": "Data Scientist"},
        {"name": "Machine Learning Engineer"},
        {"name": "AI Researcher"},
        {"name": "Data Engineer"},
        {"name": "MLOps Engineer"},
        {"name": "Computer Vision Engineer"},
        {"name": "NLP Engineer"},
        {"name": "Deep Learning Engineer"},
        {"name": "Applied Scientist"},
        {"name": "Data Analyst"},
        {"name": "Big Data Engineer"},
        {"name": "Generative AI Engineer"},
        {"name": "AI Product Manager"},
        {"name": "Quantitative Analyst"},
        {"name": "Bioinformatics Data Scientist"},
        {"name": "AI Ethics Specialist"}
      ]
    },
    {
      "name": "Cybersecurity",
      "description": "Protecting systems, networks, and programs from digital attacks.",
      "jobs": [
        {"name": "Security Analyst"},
        {"name": "Penetration Tester"},
        {"name": "Security Engineer"},
        {"name": "Incident Responder"},
        {"name": "SOC Analyst"},
        {"name": "Cryptographer"},
        {"name": "Cyber Threat Intelligence Analyst"}
        {"name": "Ethical Hacker"},
        {"name": "Red Team Specialist"},
        {"name": "Blue Team Specialist"},
        {"name": "Malware Analyst"},
        {"name": "Digital Forensics Analyst"},
        {"name": "Security Auditor"},
        {"name": "GRC Specialist"},
        {"name": "Application Security Engineer"},
        {"name": "Security Automation Engineer"},
        {"name": "Cloud Security Engineer"}
      ]
    },
    {
      "name": "Networking & Cloud Infrastructure",
      "description": "Building and maintaining network and cloud systems.",
      "jobs": [
        {"name": "Network Engineer"},
        {"name": "Cloud Engineer"},
        {"name": "Cloud Solutions Architect"},
        {"name": "Network Administrator"},
        {"name": "Infrastructure Engineer"},
        {"name": "Cloud Administrator"},
        {"name": "Kubernetes Administrator"},
        {"name": "Network Security Engineer"},
        {"name": "Cloud Migration Specialist"},
        {"name": "Infrastructure Architect"},
        {"name": "Terraform Infrastructure Engineer"}
      ]
    },
    {
      "name": "DevOps & SRE",
      "description": "Automating and managing software deployment and reliability.",
      "jobs": [
        {"name": "DevOps Engineer"},
        {"name": "Site Reliability Engineer"},
        {"name": "Platform Engineer"},
        {"name": "Build and Release Engineer"},
        {"name": "CI/CD Engineer"},
        {"name": "Automation Engineer"},
        {"name": "Observability Engineer"},
        {"name": "IaC Engineer"},
        {"name": "Release Automation Specialist"},
        {"name": "Monitoring & Logging Engineer"}
      ]
    },
    {
      "name": "Systems & Embedded",
      "description": "Developing low-level software or hardware-integrated systems.",
      "jobs": [
        {"name": "Embedded Systems Engineer"},
        {"name": "Firmware Engineer"},
        {"name": "Systems Programmer"},
        {"name": "IoT Developer"},
        {"name": "Robotics Engineer"},
        {"name": "FPGA Engineer"},
        {"name": "Hardware Engineer"},
        {"name": "Real-Time Systems Developer"},
        {"name": "ASIC/SoC Engineer"},
        {"name": "Microcontroller Developer"}
      ]
    },
    {
      "name": "Game Development",
      "description": "Creating interactive entertainment and game software.",
      "jobs": [
        {"name": "Game Developer"},
        {"name": "Game Designer"},
        {"name": "3D Graphics Programmer"},
        {"name": "Game Engine Developer"},
        {"name": "Gameplay Programmer"},
        {"name": "Technical Artist"},
        {"name": "Level Designer"},
        {"name": "Game AI Programmer"},
        {"name": "Animation Programmer"},
        {"name": "Shader Developer"}
      ]
    },
    {
      "name": "Human–Computer Interaction / UI-UX",
      "description": "Designing intuitive user interfaces and experiences.",
      "jobs": [
        {"name": "UI/UX Designer"},
        {"name": "Interaction Designer"},
        {"name": "Product Designer"},
        {"name": "Usability Engineer"},
        {"name": "UX Researcher"},
        {"name": "UI Developer"},
        {"name": "Motion Designer"},
        {"name": "Visual Designer"},
        {"name": "Product Owner"},
        {"name": "Accessibility Specialist"},
        {"name": "Design Systems Engineer"}
      ]
    },
    {
      "name": "Research & Academia",
      "description": "Pursuing scientific research and teaching in computing disciplines.",
      "jobs": [
        {"name": "Research Scientist"},
        {"name": "Postdoctoral Researcher"},
        {"name": "Teaching Assistant"},
        {"name": "Professor of Computer Science"},
        {"name": "Research Assistant"},
        {"name": "Research Lab Engineer"},
        {"name": "Curriculum Developer"},
        {"name": "Industry Research Engineer"}
      ]
    },
    {
      "name": "IT Support & Systems Administration",
      "description": "Providing technical support and managing enterprise systems.",
      "jobs": [
        {"name": "IT Support Specialist"},
        {"name": "Systems Administrator"},
        {"name": "Helpdesk Technician"},
        {"name": "IT Consultant"},
        {"name": "Technical Support Engineer"},
        {"name": "Desktop Support Engineer"},
        {"name": "IT Operations Manager"},
        {"name": "Field Service Technician"},
        {"name": "Virtualization Administrator"},
        {"name": "IT Asset Manager"}
      ]
    }
  ]
}
